{
  "baseline": {
    "bps10": {
      "ci_high": 0.0020470361165163794,
      "ci_low": 0.0009900736956793236,
      "mean": 0.0015081241798309882,
      "n": 331,
      "p_mean_gt_0": 1.0,
      "std": 0.00484005527694872,
      "win_rate": 0.5861027190332326
    },
    "bps8": {
      "ci_high": 0.0022470361165163794,
      "ci_low": 0.0011900736956793239,
      "mean": 0.0017081241798309887,
      "n": 331,
      "p_mean_gt_0": 1.0,
      "std": 0.004840055276948721,
      "win_rate": 0.6193353474320241
    },
    "gross": {
      "ci_high": 0.0030470361165163794,
      "ci_low": 0.0019900736956793242,
      "mean": 0.0025081241798309882,
      "n": 331,
      "p_mean_gt_0": 1.0,
      "std": 0.004840055276948721,
      "win_rate": 0.7371601208459214
    }
  },
  "classification": "PASS",
  "commands": [
    "ENV {\"PYTHONPATH\": \".\"} .venv/bin/python scripts/research_family_runner.py --hypothesis-id H251 --family cross_asset_regime --days 365 --timeframe 5m --horizon 12 --all-modes --wf 60 15 15 --bootstrap-iters 3000 --output-json results/archive/h251_runner_20260311T233809Z_all.json --dsn postgresql://rc_user:wemyss@localhost:5432/regime_crypto"
  ],
  "dataset": {
    "bar_count": 100112,
    "db_last_modified": {
      "BTC-USD": "2026-03-11T23:38:16+00:00",
      "ETH-USD": "2026-03-11T23:38:16+00:00"
    },
    "db_path": {
      "BTC-USD": "postgres:rc.candles",
      "ETH-USD": "postgres:rc.candles"
    },
    "end_ts": "2026-02-22T20:40:00+00:00",
    "horizon_bars": 12,
    "lookback_days": 365,
    "primary_symbols": [
      "BTC-USD"
    ],
    "secondary_symbols": [
      "ETH-USD"
    ],
    "source_windows": {
      "BTC-USD": {
        "bar_count": 100118,
        "end_ts": "2026-02-22T20:40:00+00:00",
        "start_ts": "2025-03-11T23:40:00+00:00"
      },
      "ETH-USD": {
        "bar_count": 100112,
        "end_ts": "2026-02-22T20:40:00+00:00",
        "start_ts": "2025-03-11T23:40:00+00:00"
      }
    },
    "start_ts": "2025-03-11T23:40:00+00:00",
    "timeframe": "5m"
  },
  "hypothesis_id": "H251",
  "logic_hash": null,
  "mode_classification": {
    "bps10": {
      "baseline_status": "PASS",
      "final_status": "PASS",
      "wf_status": "PASS"
    },
    "bps8": {
      "baseline_status": "PASS",
      "final_status": "PASS",
      "wf_status": "PASS"
    },
    "gross": {
      "baseline_status": "PASS",
      "final_status": "PASS",
      "wf_status": "PASS"
    }
  },
  "notes": "Append-only artifact generated by queue-driven batch runner.",
  "timestamp_utc": "2026-03-11T23:38:16+00:00",
  "walkforward": {
    "modes": {
      "bps10": {
        "aggregate": {
          "mean": 0.0014781851759730897,
          "mean_ci_high": 0.002040035241245434,
          "mean_ci_low": 0.0009160914047504883,
          "n": 255,
          "p_mean_gt_0": 1.0
        },
        "diagnostics": {
          "mae_proxy_median": -0.0006803612335488651,
          "median_hold_return": 0.0005267355292321039,
          "return_histogram_bins": [
            "(-inf,-1%)",
            "[-1%,-0.5%)",
            "[-0.5%,-0.2%)",
            "[-0.2%,0%)",
            "[0%,0.2%)",
            "[0.2%,0.5%)",
            "[0.5%,1%)",
            "[1%,inf)"
          ],
          "return_histogram_counts": [
            0,
            12,
            33,
            92,
            89,
            58,
            26,
            21
          ],
          "top10_pct_pnl_contribution": 0.8519823910732306,
          "trades_per_day": 0.9572237618990239
        },
        "folds": [
          {
            "fold_id": 1,
            "mean": 0.0021036496521317566,
            "n": 10,
            "test_end": "2025-05-26T00:00:00+00:00",
            "test_start": "2025-05-11T00:00:00+00:00"
          },
          {
            "fold_id": 2,
            "mean": 6.160862242907029e-05,
            "n": 15,
            "test_end": "2025-06-10T00:00:00+00:00",
            "test_start": "2025-05-26T00:00:00+00:00"
          },
          {
            "fold_id": 3,
            "mean": 0.0033634150287054766,
            "n": 13,
            "test_end": "2025-06-25T00:00:00+00:00",
            "test_start": "2025-06-10T00:00:00+00:00"
          },
          {
            "fold_id": 4,
            "mean": -0.0004751059895193056,
            "n": 18,
            "test_end": "2025-07-10T00:00:00+00:00",
            "test_start": "2025-06-25T00:00:00+00:00"
          },
          {
            "fold_id": 5,
            "mean": 0.0003771794605232701,
            "n": 10,
            "test_end": "2025-07-25T00:00:00+00:00",
            "test_start": "2025-07-10T00:00:00+00:00"
          },
          {
            "fold_id": 6,
            "mean": 0.0016558693735573128,
            "n": 14,
            "test_end": "2025-08-09T00:00:00+00:00",
            "test_start": "2025-07-25T00:00:00+00:00"
          },
          {
            "fold_id": 7,
            "mean": 0.003177342093460745,
            "n": 10,
            "test_end": "2025-08-24T00:00:00+00:00",
            "test_start": "2025-08-09T00:00:00+00:00"
          },
          {
            "fold_id": 8,
            "mean": 0.001202229524409594,
            "n": 17,
            "test_end": "2025-09-08T00:00:00+00:00",
            "test_start": "2025-08-24T00:00:00+00:00"
          },
          {
            "fold_id": 9,
            "mean": 0.0013672657096701429,
            "n": 11,
            "test_end": "2025-09-23T00:00:00+00:00",
            "test_start": "2025-09-08T00:00:00+00:00"
          },
          {
            "fold_id": 10,
            "mean": -0.0006723123432036149,
            "n": 18,
            "test_end": "2025-10-08T00:00:00+00:00",
            "test_start": "2025-09-23T00:00:00+00:00"
          },
          {
            "fold_id": 11,
            "mean": 0.007760075701280988,
            "n": 10,
            "test_end": "2025-10-23T00:00:00+00:00",
            "test_start": "2025-10-08T00:00:00+00:00"
          },
          {
            "fold_id": 12,
            "mean": 0.0016710482111394836,
            "n": 11,
            "test_end": "2025-11-07T00:00:00+00:00",
            "test_start": "2025-10-23T00:00:00+00:00"
          },
          {
            "fold_id": 13,
            "mean": 0.0004068147471036907,
            "n": 12,
            "test_end": "2025-11-22T00:00:00+00:00",
            "test_start": "2025-11-07T00:00:00+00:00"
          },
          {
            "fold_id": 14,
            "mean": 0.0021770289371051237,
            "n": 19,
            "test_end": "2025-12-07T00:00:00+00:00",
            "test_start": "2025-11-22T00:00:00+00:00"
          },
          {
            "fold_id": 15,
            "mean": 0.004179404107048466,
            "n": 13,
            "test_end": "2025-12-22T00:00:00+00:00",
            "test_start": "2025-12-07T00:00:00+00:00"
          },
          {
            "fold_id": 16,
            "mean": 0.000649897138226288,
            "n": 17,
            "test_end": "2026-01-06T00:00:00+00:00",
            "test_start": "2025-12-22T00:00:00+00:00"
          },
          {
            "fold_id": 17,
            "mean": 0.0008962639451219895,
            "n": 13,
            "test_end": "2026-01-21T00:00:00+00:00",
            "test_start": "2026-01-06T00:00:00+00:00"
          },
          {
            "fold_id": 18,
            "mean": -0.0013693219517567628,
            "n": 10,
            "test_end": "2026-02-05T00:00:00+00:00",
            "test_start": "2026-01-21T00:00:00+00:00"
          },
          {
            "fold_id": 19,
            "mean": 0.002295299037440532,
            "n": 14,
            "test_end": "2026-02-20T00:00:00+00:00",
            "test_start": "2026-02-05T00:00:00+00:00"
          }
        ],
        "positive_folds": {
          "count": 16,
          "pct": 84.21052631578948,
          "total": 19
        }
      },
      "bps8": {
        "aggregate": {
          "mean": 0.00167818517597309,
          "mean_ci_high": 0.0022400352412454347,
          "mean_ci_low": 0.0011160914047504886,
          "n": 255,
          "p_mean_gt_0": 1.0
        },
        "diagnostics": {
          "mae_proxy_median": -0.0006803612335488651,
          "median_hold_return": 0.0007267355292321038,
          "return_histogram_bins": [
            "(-inf,-1%)",
            "[-1%,-0.5%)",
            "[-0.5%,-0.2%)",
            "[-0.2%,0%)",
            "[0%,0.2%)",
            "[0.2%,0.5%)",
            "[0.5%,1%)",
            "[1%,inf)"
          ],
          "return_histogram_counts": [
            0,
            10,
            30,
            86,
            92,
            65,
            26,
            22
          ],
          "top10_pct_pnl_contribution": 0.76425301323435,
          "trades_per_day": 0.9572237618990239
        },
        "folds": [
          {
            "fold_id": 1,
            "mean": 0.0023036496521317566,
            "n": 10,
            "test_end": "2025-05-26T00:00:00+00:00",
            "test_start": "2025-05-11T00:00:00+00:00"
          },
          {
            "fold_id": 2,
            "mean": 0.00026160862242907034,
            "n": 15,
            "test_end": "2025-06-10T00:00:00+00:00",
            "test_start": "2025-05-26T00:00:00+00:00"
          },
          {
            "fold_id": 3,
            "mean": 0.0035634150287054763,
            "n": 13,
            "test_end": "2025-06-25T00:00:00+00:00",
            "test_start": "2025-06-10T00:00:00+00:00"
          },
          {
            "fold_id": 4,
            "mean": -0.00027510598951930546,
            "n": 18,
            "test_end": "2025-07-10T00:00:00+00:00",
            "test_start": "2025-06-25T00:00:00+00:00"
          },
          {
            "fold_id": 5,
            "mean": 0.0005771794605232701,
            "n": 10,
            "test_end": "2025-07-25T00:00:00+00:00",
            "test_start": "2025-07-10T00:00:00+00:00"
          },
          {
            "fold_id": 6,
            "mean": 0.0018558693735573136,
            "n": 14,
            "test_end": "2025-08-09T00:00:00+00:00",
            "test_start": "2025-07-25T00:00:00+00:00"
          },
          {
            "fold_id": 7,
            "mean": 0.0033773420934607454,
            "n": 10,
            "test_end": "2025-08-24T00:00:00+00:00",
            "test_start": "2025-08-09T00:00:00+00:00"
          },
          {
            "fold_id": 8,
            "mean": 0.001402229524409594,
            "n": 17,
            "test_end": "2025-09-08T00:00:00+00:00",
            "test_start": "2025-08-24T00:00:00+00:00"
          },
          {
            "fold_id": 9,
            "mean": 0.0015672657096701432,
            "n": 11,
            "test_end": "2025-09-23T00:00:00+00:00",
            "test_start": "2025-09-08T00:00:00+00:00"
          },
          {
            "fold_id": 10,
            "mean": -0.00047231234320361485,
            "n": 18,
            "test_end": "2025-10-08T00:00:00+00:00",
            "test_start": "2025-09-23T00:00:00+00:00"
          },
          {
            "fold_id": 11,
            "mean": 0.007960075701280989,
            "n": 10,
            "test_end": "2025-10-23T00:00:00+00:00",
            "test_start": "2025-10-08T00:00:00+00:00"
          },
          {
            "fold_id": 12,
            "mean": 0.0018710482111394843,
            "n": 11,
            "test_end": "2025-11-07T00:00:00+00:00",
            "test_start": "2025-10-23T00:00:00+00:00"
          },
          {
            "fold_id": 13,
            "mean": 0.0006068147471036907,
            "n": 12,
            "test_end": "2025-11-22T00:00:00+00:00",
            "test_start": "2025-11-07T00:00:00+00:00"
          },
          {
            "fold_id": 14,
            "mean": 0.002377028937105124,
            "n": 19,
            "test_end": "2025-12-07T00:00:00+00:00",
            "test_start": "2025-11-22T00:00:00+00:00"
          },
          {
            "fold_id": 15,
            "mean": 0.004379404107048466,
            "n": 13,
            "test_end": "2025-12-22T00:00:00+00:00",
            "test_start": "2025-12-07T00:00:00+00:00"
          },
          {
            "fold_id": 16,
            "mean": 0.0008498971382262877,
            "n": 17,
            "test_end": "2026-01-06T00:00:00+00:00",
            "test_start": "2025-12-22T00:00:00+00:00"
          },
          {
            "fold_id": 17,
            "mean": 0.0010962639451219897,
            "n": 13,
            "test_end": "2026-01-21T00:00:00+00:00",
            "test_start": "2026-01-06T00:00:00+00:00"
          },
          {
            "fold_id": 18,
            "mean": -0.0011693219517567625,
            "n": 10,
            "test_end": "2026-02-05T00:00:00+00:00",
            "test_start": "2026-01-21T00:00:00+00:00"
          },
          {
            "fold_id": 19,
            "mean": 0.0024952990374405323,
            "n": 14,
            "test_end": "2026-02-20T00:00:00+00:00",
            "test_start": "2026-02-05T00:00:00+00:00"
          }
        ],
        "positive_folds": {
          "count": 16,
          "pct": 84.21052631578948,
          "total": 19
        }
      },
      "gross": {
        "aggregate": {
          "mean": 0.00247818517597309,
          "mean_ci_high": 0.0030400352412454346,
          "mean_ci_low": 0.0019160914047504883,
          "n": 255,
          "p_mean_gt_0": 1.0
        },
        "diagnostics": {
          "mae_proxy_median": -0.0006803612335488651,
          "median_hold_return": 0.0015267355292321039,
          "return_histogram_bins": [
            "(-inf,-1%)",
            "[-1%,-0.5%)",
            "[-0.5%,-0.2%)",
            "[-0.2%,0%)",
            "[0%,0.2%)",
            "[0.2%,0.5%)",
            "[0.5%,1%)",
            "[1%,inf)"
          ],
          "return_histogram_counts": [
            0,
            8,
            23,
            56,
            100,
            81,
            40,
            23
          ],
          "top10_pct_pnl_contribution": 0.5532478372318447,
          "trades_per_day": 0.9572237618990239
        },
        "folds": [
          {
            "fold_id": 1,
            "mean": 0.003103649652131757,
            "n": 10,
            "test_end": "2025-05-26T00:00:00+00:00",
            "test_start": "2025-05-11T00:00:00+00:00"
          },
          {
            "fold_id": 2,
            "mean": 0.0010616086224290702,
            "n": 15,
            "test_end": "2025-06-10T00:00:00+00:00",
            "test_start": "2025-05-26T00:00:00+00:00"
          },
          {
            "fold_id": 3,
            "mean": 0.004363415028705477,
            "n": 13,
            "test_end": "2025-06-25T00:00:00+00:00",
            "test_start": "2025-06-10T00:00:00+00:00"
          },
          {
            "fold_id": 4,
            "mean": 0.0005248940104806946,
            "n": 18,
            "test_end": "2025-07-10T00:00:00+00:00",
            "test_start": "2025-06-25T00:00:00+00:00"
          },
          {
            "fold_id": 5,
            "mean": 0.0013771794605232702,
            "n": 10,
            "test_end": "2025-07-25T00:00:00+00:00",
            "test_start": "2025-07-10T00:00:00+00:00"
          },
          {
            "fold_id": 6,
            "mean": 0.002655869373557313,
            "n": 14,
            "test_end": "2025-08-09T00:00:00+00:00",
            "test_start": "2025-07-25T00:00:00+00:00"
          },
          {
            "fold_id": 7,
            "mean": 0.004177342093460745,
            "n": 10,
            "test_end": "2025-08-24T00:00:00+00:00",
            "test_start": "2025-08-09T00:00:00+00:00"
          },
          {
            "fold_id": 8,
            "mean": 0.0022022295244095943,
            "n": 17,
            "test_end": "2025-09-08T00:00:00+00:00",
            "test_start": "2025-08-24T00:00:00+00:00"
          },
          {
            "fold_id": 9,
            "mean": 0.002367265709670143,
            "n": 11,
            "test_end": "2025-09-23T00:00:00+00:00",
            "test_start": "2025-09-08T00:00:00+00:00"
          },
          {
            "fold_id": 10,
            "mean": 0.00032768765679638514,
            "n": 18,
            "test_end": "2025-10-08T00:00:00+00:00",
            "test_start": "2025-09-23T00:00:00+00:00"
          },
          {
            "fold_id": 11,
            "mean": 0.008760075701280989,
            "n": 10,
            "test_end": "2025-10-23T00:00:00+00:00",
            "test_start": "2025-10-08T00:00:00+00:00"
          },
          {
            "fold_id": 12,
            "mean": 0.0026710482111394836,
            "n": 11,
            "test_end": "2025-11-07T00:00:00+00:00",
            "test_start": "2025-10-23T00:00:00+00:00"
          },
          {
            "fold_id": 13,
            "mean": 0.0014068147471036907,
            "n": 12,
            "test_end": "2025-11-22T00:00:00+00:00",
            "test_start": "2025-11-07T00:00:00+00:00"
          },
          {
            "fold_id": 14,
            "mean": 0.0031770289371051245,
            "n": 19,
            "test_end": "2025-12-07T00:00:00+00:00",
            "test_start": "2025-11-22T00:00:00+00:00"
          },
          {
            "fold_id": 15,
            "mean": 0.005179404107048467,
            "n": 13,
            "test_end": "2025-12-22T00:00:00+00:00",
            "test_start": "2025-12-07T00:00:00+00:00"
          },
          {
            "fold_id": 16,
            "mean": 0.001649897138226288,
            "n": 17,
            "test_end": "2026-01-06T00:00:00+00:00",
            "test_start": "2025-12-22T00:00:00+00:00"
          },
          {
            "fold_id": 17,
            "mean": 0.0018962639451219898,
            "n": 13,
            "test_end": "2026-01-21T00:00:00+00:00",
            "test_start": "2026-01-06T00:00:00+00:00"
          },
          {
            "fold_id": 18,
            "mean": -0.0003693219517567625,
            "n": 10,
            "test_end": "2026-02-05T00:00:00+00:00",
            "test_start": "2026-01-21T00:00:00+00:00"
          },
          {
            "fold_id": 19,
            "mean": 0.0032952990374405322,
            "n": 14,
            "test_end": "2026-02-20T00:00:00+00:00",
            "test_start": "2026-02-05T00:00:00+00:00"
          }
        ],
        "positive_folds": {
          "count": 18,
          "pct": 94.73684210526316,
          "total": 19
        }
      }
    },
    "split": {
      "step_days": 15,
      "test_days": 15,
      "train_days": 60
    }
  }
}