{
  "baseline": {
    "bps10": {
      "ci_high": -0.0004452733268094805,
      "ci_low": -0.0010215818158910448,
      "mean": -0.0007342110863248122,
      "n": 969,
      "p_mean_gt_0": 0.0,
      "std": 0.004549650796057693,
      "win_rate": 0.4055727554179567
    },
    "bps8": {
      "ci_high": -0.00024527332680948004,
      "ci_low": -0.0008215818158910442,
      "mean": -0.0005342110863248119,
      "n": 969,
      "p_mean_gt_0": 0.0,
      "std": 0.004549650796057693,
      "win_rate": 0.43653250773993807
    },
    "gross": {
      "ci_high": 0.0005547266731905198,
      "ci_low": -2.1581815891044157e-05,
      "mean": 0.00026578891367518806,
      "n": 969,
      "p_mean_gt_0": 0.962,
      "std": 0.004549650796057693,
      "win_rate": 0.5510835913312694
    }
  },
  "classification": "FAIL",
  "commands": [
    "ENV {\"PYTHONPATH\": \".\"} .venv/bin/python scripts/research_family_runner.py --hypothesis-id H51 --family mean_reversion --days 365 --timeframe 5m --horizon 6 --all-modes --wf 60 15 15 --bootstrap-iters 3000 --output-json results/archive/h51_runner_20260223T064359Z_all.json --dsn postgresql://rc_user:wemyss@localhost:5432/regime_crypto"
  ],
  "dataset": {
    "bar_count": 104923,
    "db_last_modified": {
      "BTC-USD": "2026-02-23T06:44:04+00:00",
      "ETH-USD": "2026-02-23T06:44:04+00:00"
    },
    "db_path": {
      "BTC-USD": "postgres:rc.candles",
      "ETH-USD": "postgres:rc.candles"
    },
    "end_ts": "2026-02-22T20:40:00+00:00",
    "horizon_bars": 6,
    "lookback_days": 365,
    "primary_symbols": [
      "BTC-USD"
    ],
    "secondary_symbols": [
      "ETH-USD"
    ],
    "source_windows": {
      "BTC-USD": {
        "bar_count": 104929,
        "end_ts": "2026-02-22T20:40:00+00:00",
        "start_ts": "2025-02-23T06:45:00+00:00"
      },
      "ETH-USD": {
        "bar_count": 104923,
        "end_ts": "2026-02-22T20:40:00+00:00",
        "start_ts": "2025-02-23T06:45:00+00:00"
      }
    },
    "start_ts": "2025-02-23T06:45:00+00:00",
    "timeframe": "5m"
  },
  "hypothesis_id": "H51",
  "logic_hash": null,
  "mode_classification": {
    "bps10": {
      "baseline_status": "FAIL",
      "final_status": "FAIL",
      "wf_status": "FAIL"
    },
    "bps8": {
      "baseline_status": "FAIL",
      "final_status": "FAIL",
      "wf_status": "FAIL"
    },
    "gross": {
      "baseline_status": "BORDERLINE",
      "final_status": "BORDERLINE",
      "wf_status": "BORDERLINE"
    }
  },
  "notes": "Append-only artifact generated by queue-driven batch runner.",
  "timestamp_utc": "2026-02-23T06:44:04+00:00",
  "walkforward": {
    "modes": {
      "bps10": {
        "aggregate": {
          "mean": -0.0007794123020936813,
          "mean_ci_high": -0.00042809344848699786,
          "mean_ci_low": -0.0011215164214753066,
          "n": 741,
          "p_mean_gt_0": 0.0
        },
        "diagnostics": {
          "mae_proxy_median": -0.0010678675383426484,
          "median_hold_return": -0.0006352644632058304,
          "return_histogram_bins": [
            "(-inf,-1%)",
            "[-1%,-0.5%)",
            "[-0.5%,-0.2%)",
            "[-0.2%,0%)",
            "[0%,0.2%)",
            "[0.2%,0.5%)",
            "[0.5%,1%)",
            "[1%,inf)"
          ],
          "return_histogram_counts": [
            32,
            76,
            198,
            270,
            196,
            137,
            41,
            19
          ],
          "top10_pct_pnl_contribution": -0.9748618914329982,
          "trades_per_day": 3.4646670308387546
        },
        "folds": [
          {
            "fold_id": 1,
            "mean": -0.0006098006341439946,
            "n": 37,
            "test_end": "2025-08-02T00:00:00+00:00",
            "test_start": "2025-07-18T00:00:00+00:00"
          },
          {
            "fold_id": 2,
            "mean": -0.00014614033675669212,
            "n": 29,
            "test_end": "2025-08-17T00:00:00+00:00",
            "test_start": "2025-08-02T00:00:00+00:00"
          },
          {
            "fold_id": 3,
            "mean": -0.0008954935294359221,
            "n": 53,
            "test_end": "2025-09-01T00:00:00+00:00",
            "test_start": "2025-08-17T00:00:00+00:00"
          },
          {
            "fold_id": 4,
            "mean": -0.0011394727124682746,
            "n": 37,
            "test_end": "2025-09-16T00:00:00+00:00",
            "test_start": "2025-09-01T00:00:00+00:00"
          },
          {
            "fold_id": 5,
            "mean": -0.00019431157441533725,
            "n": 76,
            "test_end": "2025-10-01T00:00:00+00:00",
            "test_start": "2025-09-16T00:00:00+00:00"
          },
          {
            "fold_id": 6,
            "mean": 0.00021239238593833776,
            "n": 20,
            "test_end": "2025-10-16T00:00:00+00:00",
            "test_start": "2025-10-01T00:00:00+00:00"
          },
          {
            "fold_id": 7,
            "mean": -0.001365435547323567,
            "n": 69,
            "test_end": "2025-10-31T00:00:00+00:00",
            "test_start": "2025-10-16T00:00:00+00:00"
          },
          {
            "fold_id": 8,
            "mean": -0.0010829149013859788,
            "n": 68,
            "test_end": "2025-11-15T00:00:00+00:00",
            "test_start": "2025-10-31T00:00:00+00:00"
          },
          {
            "fold_id": 9,
            "mean": -0.00047707440113271306,
            "n": 24,
            "test_end": "2025-11-30T00:00:00+00:00",
            "test_start": "2025-11-15T00:00:00+00:00"
          },
          {
            "fold_id": 10,
            "mean": -0.0009194033822286328,
            "n": 76,
            "test_end": "2025-12-15T00:00:00+00:00",
            "test_start": "2025-11-30T00:00:00+00:00"
          },
          {
            "fold_id": 11,
            "mean": -0.00039939823664939835,
            "n": 21,
            "test_end": "2025-12-30T00:00:00+00:00",
            "test_start": "2025-12-15T00:00:00+00:00"
          },
          {
            "fold_id": 12,
            "mean": -0.00044211721931648507,
            "n": 36,
            "test_end": "2026-01-14T00:00:00+00:00",
            "test_start": "2025-12-30T00:00:00+00:00"
          },
          {
            "fold_id": 13,
            "mean": -0.0009725354321589624,
            "n": 79,
            "test_end": "2026-01-29T00:00:00+00:00",
            "test_start": "2026-01-14T00:00:00+00:00"
          },
          {
            "fold_id": 14,
            "mean": -0.000864575452777538,
            "n": 116,
            "test_end": "2026-02-13T00:00:00+00:00",
            "test_start": "2026-01-29T00:00:00+00:00"
          }
        ],
        "positive_folds": {
          "count": 1,
          "pct": 7.142857142857143,
          "total": 14
        }
      },
      "bps8": {
        "aggregate": {
          "mean": -0.0005794123020936811,
          "mean_ci_high": -0.00022809344848699755,
          "mean_ci_low": -0.0009215164214753064,
          "n": 741,
          "p_mean_gt_0": 0.0006666666666666666
        },
        "diagnostics": {
          "mae_proxy_median": -0.0010678675383426484,
          "median_hold_return": -0.00043526446320583045,
          "return_histogram_bins": [
            "(-inf,-1%)",
            "[-1%,-0.5%)",
            "[-0.5%,-0.2%)",
            "[-0.2%,0%)",
            "[0%,0.2%)",
            "[0.2%,0.5%)",
            "[0.5%,1%)",
            "[1%,inf)"
          ],
          "return_histogram_counts": [
            31,
            73,
            177,
            265,
            212,
            147,
            45,
            19
          ],
          "top10_pct_pnl_contribution": -1.3773114542089395,
          "trades_per_day": 3.4646670308387546
        },
        "folds": [
          {
            "fold_id": 1,
            "mean": -0.00040980063414399425,
            "n": 37,
            "test_end": "2025-08-02T00:00:00+00:00",
            "test_start": "2025-07-18T00:00:00+00:00"
          },
          {
            "fold_id": 2,
            "mean": 5.385966324330786e-05,
            "n": 29,
            "test_end": "2025-08-17T00:00:00+00:00",
            "test_start": "2025-08-02T00:00:00+00:00"
          },
          {
            "fold_id": 3,
            "mean": -0.0006954935294359221,
            "n": 53,
            "test_end": "2025-09-01T00:00:00+00:00",
            "test_start": "2025-08-17T00:00:00+00:00"
          },
          {
            "fold_id": 4,
            "mean": -0.0009394727124682746,
            "n": 37,
            "test_end": "2025-09-16T00:00:00+00:00",
            "test_start": "2025-09-01T00:00:00+00:00"
          },
          {
            "fold_id": 5,
            "mean": 5.688425584662807e-06,
            "n": 76,
            "test_end": "2025-10-01T00:00:00+00:00",
            "test_start": "2025-09-16T00:00:00+00:00"
          },
          {
            "fold_id": 6,
            "mean": 0.0004123923859383376,
            "n": 20,
            "test_end": "2025-10-16T00:00:00+00:00",
            "test_start": "2025-10-01T00:00:00+00:00"
          },
          {
            "fold_id": 7,
            "mean": -0.0011654355473235665,
            "n": 69,
            "test_end": "2025-10-31T00:00:00+00:00",
            "test_start": "2025-10-16T00:00:00+00:00"
          },
          {
            "fold_id": 8,
            "mean": -0.0008829149013859784,
            "n": 68,
            "test_end": "2025-11-15T00:00:00+00:00",
            "test_start": "2025-10-31T00:00:00+00:00"
          },
          {
            "fold_id": 9,
            "mean": -0.00027707440113271275,
            "n": 24,
            "test_end": "2025-11-30T00:00:00+00:00",
            "test_start": "2025-11-15T00:00:00+00:00"
          },
          {
            "fold_id": 10,
            "mean": -0.0007194033822286325,
            "n": 76,
            "test_end": "2025-12-15T00:00:00+00:00",
            "test_start": "2025-11-30T00:00:00+00:00"
          },
          {
            "fold_id": 11,
            "mean": -0.00019939823664939826,
            "n": 21,
            "test_end": "2025-12-30T00:00:00+00:00",
            "test_start": "2025-12-15T00:00:00+00:00"
          },
          {
            "fold_id": 12,
            "mean": -0.0002421172193164852,
            "n": 36,
            "test_end": "2026-01-14T00:00:00+00:00",
            "test_start": "2025-12-30T00:00:00+00:00"
          },
          {
            "fold_id": 13,
            "mean": -0.0007725354321589622,
            "n": 79,
            "test_end": "2026-01-29T00:00:00+00:00",
            "test_start": "2026-01-14T00:00:00+00:00"
          },
          {
            "fold_id": 14,
            "mean": -0.0006645754527775373,
            "n": 116,
            "test_end": "2026-02-13T00:00:00+00:00",
            "test_start": "2026-01-29T00:00:00+00:00"
          }
        ],
        "positive_folds": {
          "count": 3,
          "pct": 21.428571428571427,
          "total": 14
        }
      },
      "gross": {
        "aggregate": {
          "mean": 0.00022058769790631895,
          "mean_ci_high": 0.0005719065515130024,
          "mean_ci_low": -0.0001215164214753063,
          "n": 741,
          "p_mean_gt_0": 0.8993333333333333
        },
        "diagnostics": {
          "mae_proxy_median": -0.0010678675383426484,
          "median_hold_return": 0.0003647355367941696,
          "return_histogram_bins": [
            "(-inf,-1%)",
            "[-1%,-0.5%)",
            "[-0.5%,-0.2%)",
            "[-0.2%,0%)",
            "[0%,0.2%)",
            "[0.2%,0.5%)",
            "[0.5%,1%)",
            "[1%,inf)"
          ],
          "return_histogram_counts": [
            25,
            57,
            111,
            242,
            260,
            192,
            61,
            21
          ],
          "top10_pct_pnl_contribution": 3.069569743217817,
          "trades_per_day": 3.4646670308387546
        },
        "folds": [
          {
            "fold_id": 1,
            "mean": 0.00039019936585600563,
            "n": 37,
            "test_end": "2025-08-02T00:00:00+00:00",
            "test_start": "2025-07-18T00:00:00+00:00"
          },
          {
            "fold_id": 2,
            "mean": 0.0008538596632433079,
            "n": 29,
            "test_end": "2025-08-17T00:00:00+00:00",
            "test_start": "2025-08-02T00:00:00+00:00"
          },
          {
            "fold_id": 3,
            "mean": 0.00010450647056407828,
            "n": 53,
            "test_end": "2025-09-01T00:00:00+00:00",
            "test_start": "2025-08-17T00:00:00+00:00"
          },
          {
            "fold_id": 4,
            "mean": -0.00013947271246827442,
            "n": 37,
            "test_end": "2025-09-16T00:00:00+00:00",
            "test_start": "2025-09-01T00:00:00+00:00"
          },
          {
            "fold_id": 5,
            "mean": 0.0008056884255846628,
            "n": 76,
            "test_end": "2025-10-01T00:00:00+00:00",
            "test_start": "2025-09-16T00:00:00+00:00"
          },
          {
            "fold_id": 6,
            "mean": 0.0012123923859383378,
            "n": 20,
            "test_end": "2025-10-16T00:00:00+00:00",
            "test_start": "2025-10-01T00:00:00+00:00"
          },
          {
            "fold_id": 7,
            "mean": -0.0003654355473235666,
            "n": 69,
            "test_end": "2025-10-31T00:00:00+00:00",
            "test_start": "2025-10-16T00:00:00+00:00"
          },
          {
            "fold_id": 8,
            "mean": -8.291490138597823e-05,
            "n": 68,
            "test_end": "2025-11-15T00:00:00+00:00",
            "test_start": "2025-10-31T00:00:00+00:00"
          },
          {
            "fold_id": 9,
            "mean": 0.0005229255988672873,
            "n": 24,
            "test_end": "2025-11-30T00:00:00+00:00",
            "test_start": "2025-11-15T00:00:00+00:00"
          },
          {
            "fold_id": 10,
            "mean": 8.059661777136771e-05,
            "n": 76,
            "test_end": "2025-12-15T00:00:00+00:00",
            "test_start": "2025-11-30T00:00:00+00:00"
          },
          {
            "fold_id": 11,
            "mean": 0.0006006017633506019,
            "n": 21,
            "test_end": "2025-12-30T00:00:00+00:00",
            "test_start": "2025-12-15T00:00:00+00:00"
          },
          {
            "fold_id": 12,
            "mean": 0.000557882780683515,
            "n": 36,
            "test_end": "2026-01-14T00:00:00+00:00",
            "test_start": "2025-12-30T00:00:00+00:00"
          },
          {
            "fold_id": 13,
            "mean": 2.7464567841038154e-05,
            "n": 79,
            "test_end": "2026-01-29T00:00:00+00:00",
            "test_start": "2026-01-14T00:00:00+00:00"
          },
          {
            "fold_id": 14,
            "mean": 0.00013542454722246264,
            "n": 116,
            "test_end": "2026-02-13T00:00:00+00:00",
            "test_start": "2026-01-29T00:00:00+00:00"
          }
        ],
        "positive_folds": {
          "count": 11,
          "pct": 78.57142857142857,
          "total": 14
        }
      }
    },
    "split": {
      "step_days": 15,
      "test_days": 15,
      "train_days": 60
    }
  }
}